daac/__init__.py
daac/p1.py
daac/p2.py
daac/p3.py
daac/p4.py
daac/p5.py
daac/p6.py
daac/p7.py
daac/program.py
daac/programs.py
davml/__init__.py
davml/chat.py
davml/m1.py
davml/m2.py
davml/m3.py
davml/m4.py
davml/m5.py
davml/m6.py
davml/m7.py
davml/m8.py
davml/m9.py
davml/p1.py
davml/p2.py
davml/p3.py
davml/p4.py
davml/p5.py
davml/p6.py
davml/p7.py
davml/p8.py
davml/program.py
davml/programs.py
davml-2.0.dist-info/METADATA
davml-2.0.dist-info/WHEEL
davml-2.0.dist-info/entry_points.txt
davml-2.0.dist-info/top_level.txt
davml-2.0.dist-info/RECORD
